torrent_playlist/__init__.py
torrent_playlist/__main__.py
animethemes_torrent_playlist-1.0.dist-info/LICENSE
animethemes_torrent_playlist-1.0.dist-info/METADATA
animethemes_torrent_playlist-1.0.dist-info/WHEEL
animethemes_torrent_playlist-1.0.dist-info/top_level.txt
animethemes_torrent_playlist-1.0.dist-info/RECORD
