Metadata-Version: 2.1
Name: animethemes-torrent-playlist
Version: 1.0
Summary: Download the selected torrent files matching your AnimeThemes playlist
Home-page: https://github.com/AnimeThemes/animethemes-torrent-playlist
Author: AnimeThemes
Author-email: admin@animethemes.moe
Classifier: Intended Audience :: Developers
Classifier: Programming Language :: Python :: 3
Classifier: Programming Language :: Python :: 3.6
Classifier: Programming Language :: Python :: 3.7
Classifier: Programming Language :: Python :: 3.8
Classifier: Programming Language :: Python :: 3.9
Classifier: Programming Language :: Python :: 3.10
Classifier: Programming Language :: Python :: 3.11
Classifier: License :: OSI Approved :: MIT License
Classifier: Natural Language :: English
Classifier: Operating System :: OS Independent
Requires-Python: >=3.6
License-File: LICENSE
